torch_tract/__init__.py
torch_tract/tract.py
torch_tract-1.0.0.dist-info/licenses/LICENSE
torch_tract-1.0.0.dist-info/METADATA
torch_tract-1.0.0.dist-info/WHEEL
torch_tract-1.0.0.dist-info/top_level.txt
torch_tract-1.0.0.dist-info/RECORD
